

[
  {
    "ID": 27,
    "Type": "simple",
    "SKU": "",
    "Name": "Faglig vurdering",
    "Published": 1,
    "Is featured?": 0,
    "Visibility in catalog": "visible",
    "Short description": "01.11.22",
    "Description": "Vurdering av linje og undervisning/veiledning",
    "Date sale price starts": "",
    "Date sale price ends": "",
    "Tax status": "taxable",
    "Tax class": "",
    "In stock?": 1,
    "Stock": "",
    "Low stock amount": "",
    "Backorders allowed?": 0,
    "Sold individually?": 0,
    "Weight (kg)": "",
    "Length (cm)": "",
    "Width (cm)": "",
    "Height (cm)": "",
    "Allow customer reviews?": 1,
    "Purchase note": "",
    "Sale price": "",
    "Regular price": 1,
    "categories": ["ANSATT", "Faglig ansvarlig", "STUDENT", "Student - Campus", "Student-Online"],
    "Tags": "Rapporter/Evalueringer",
    "Shipping class": "",
    "Images": "",
    "Download limit": "",
    "Download expiry days": "",
    "Parent": "",
    "Grouped products": "",
    "Upsells": "",
    "Cross-sells": "",
    "External URL": "",
    "Button text": "",
    "Position": 0,
    "Meta: _wp_old_date": "2022-04-07",
    "Meta: _botiga_page_builder_mode": 0,
    "Meta: _botiga_sidebar_layout": "",
    "Meta: _botiga_disable_header_transparent": 0
  },
  {
    "ID": 28,
    "Type": "simple",
    "SKU": "",
    "Name": "Tilfredsundersøkelse",
    "Published": 1,
    "Is featured?": 0,
    "Visibility in catalog": "visible",
    "Short description": "22.09.22",
    "Description": "For hver enkelt campus",
    "Date sale price starts": "",
    "Date sale price ends": "",
    "Tax status": "taxable",
    "Tax class": "",
    "In stock?": 1,
    "Stock": "",
    "Low stock amount": "",
    "Backorders allowed?": 0,
    "Sold individually?": 0,
    "Weight (kg)": "",
    "Length (cm)": "",
    "Width (cm)": "",
    "Height (cm)": "",
    "Allow customer reviews?": 1,
    "Purchase note": "",
    "Sale price": "",
    "Regular price": 1,
    "categories": ["Administrativt", "ANSATT", "Overordnet ansvar", "STUDENT", "Student - Campus"],
    "Tags": "Rapporter/Evalueringer",
    "Shipping class": "",
    "Images": "",
    "Download limit": "",
    "Download expiry days": "",
    "Parent": "",
    "Grouped products": "",
    "Upsells": "",
    "Cross-sells": "",
    "External URL": "",
    "Button text": "",
    "Position": 0,
    "Meta: _wp_old_date": "2020-09-22",
    "Meta: _botiga_page_builder_mode": 0,
    "Meta: _botiga_sidebar_layout": "",
    "Meta: _botiga_disable_header_transparent": 0
  },
  {
    "ID": 31,
    "Type": "simple",
    "SKU": "",
    "Name": "Helhetsvurdering",
    "Published": 1,
    "Is featured?": 0,
    "Visibility in catalog": "visible",
    "Short description": "TBA",
    "Description": "Uteksaminerende studenter",
    "Date sale price starts": "",
    "Date sale price ends": "",
    "Tax status": "taxable",
    "Tax class": "",
    "In stock?": 1,
    "Stock": "",
    "Low stock amount": "",
    "Backorders allowed?": 0,
    "Sold individually?": 0,
    "Weight (kg)": "",
    "Length (cm)": "",
    "Width (cm)": "",
    "Height (cm)": "",
    "Allow customer reviews?": 1,
    "Purchase note": "",
    "Sale price": "",
    "Regular price": 1,
    "categories": ["STUDENT", "Student - Campus", "Student-Online"],
    "Tags": "Rapporter/Evalueringer",
    "Shipping class": "",
    "Images": "",
    "Download limit": "",
    "Download expiry days": "",
    "Parent": "",
    "Grouped products": "",
    "Upsells": "",
    "Cross-sells": "",
    "External URL": "",
    "Button text": "",
    "Position": 0,
    "Meta: _wp_old_date": "2020-10-01",
    "Meta: _botiga_page_builder_mode": 0,
    "Meta: _botiga_sidebar_layout": "",
    "Meta: _botiga_disable_header_transparent": 0
  },
  {
    "ID": 33,
    "Type": "simple",
    "SKU": "",
    "Name": "Evaluering - Søknadsprosess",
    "Published": 1,
    "Is featured?": 0,
    "Visibility in catalog": "visible",
    "Short description": "20.08.22",
    "Description": "Søknadsprosess",
    "Date sale price starts": "",
    "Date sale price ends": "",
    "Tax status": "taxable",
    "Tax class": "",
    "In stock?": 1,
    "Stock": "",
    "Low stock amount": "",
    "Backorders allowed?": 0,
    "Sold individually?": 0,
    "Weight (kg)": "",
    "Length (cm)": "",
    "Width (cm)": "",
    "Height (cm)": "",
    "Allow customer reviews?": 1,
    "Purchase note": "",
    "Sale price": "",
    "Regular price": 1,
    "categories": ["Administrativt", "ANSATT", "Ny student", "Overordnet ansvar", "STUDENT"],
    "Tags": "Rapporter/Evalueringer",
    "Shipping class": "",
    "Images": "",
    "Download limit": "",
    "Download expiry days": "",
    "Parent": "",
    "Grouped products": "",
    "Upsells": "",
    "Cross-sells": "",
    "External URL": "",
    "Button text": "",
    "Position": 0,
    "Meta: _wp_old_date": "2022-04-12",
    "Meta: _botiga_page_builder_mode": 0,
    "Meta: _botiga_sidebar_layout": "",
    "Meta: _botiga_disable_header_transparent": 0
  },
  {
    "ID": 34,
    "Type": "simple",
    "SKU": "",
    "Name": "NOKUT",
    "Published": 1,
    "Is featured?": 0,
    "Visibility in catalog": "visible",
    "Short description": "01.4.23",
    "Description": "Studiebarometer",
    "Date sale price starts": "",
    "Date sale price ends": "",
    "Tax status": "taxable",
    "Tax class": "",
    "In stock?": 1,
    "Stock": "",
    "Low stock amount": "",
    "Backorders allowed?": 0,
    "Sold individually?": 0,
    "Weight (kg)": "",
    "Length (cm)": "",
    "Width (cm)": "",
    "Height (cm)": "",
    "Allow customer reviews?": 1,
    "Purchase note": "",
    "Sale price": "",
    "Regular price": 1,
    "categories": ["Administrativt", "ANSATT", "Overordnet ansvar", "STUDENT", "Student - Campus", "Student-Online"],
    "Tags": "Rapporter/Evalueringer",
    "Shipping class": "",
    "Images": "",
    "Download limit": "",
    "Download expiry days": "",
    "Parent": "",
    "Grouped products": "",
    "Upsells": "",
    "Cross-sells": "",
    "External URL": "",
    "Button text": "",
    "Position": 0,
    "Meta: _wp_old_date": "2022-04-12",
    "Meta: _botiga_page_builder_mode": 0,
    "Meta: _botiga_sidebar_layout": "",
    "Meta: _botiga_disable_header_transparent": 0
  },
  {
    "ID": 35,
    "Type": "simple",
    "SKU": "",
    "Name": "NOROFF Intern kvalitetsundersøkelse",
    "Published": 1,
    "Is featured?": 0,
    "Visibility in catalog": "visible",
    "Short description": "01.11.22",
    "Description": "Intern kvalitetsundersøkelse",
    "Date sale price starts": "",
    "Date sale price ends": "",
    "Tax status": "taxable",
    "Tax class": "",
    "In stock?": 1,
    "Stock": "",
    "Low stock amount": "",
    "Backorders allowed?": 0,
    "Sold individually?": 0,
    "Weight (kg)": "",
    "Length (cm)": "",
    "Width (cm)": "",
    "Height (cm)": "",
    "Allow customer reviews?": 1,
    "Purchase note": "",
    "Sale price": "",
    "Regular price": 1,
    "categories": ["Administrativt", "ANSATT", "Overordnet ansvar", "STUDENT", "Student - Campus", "Student-Online"],
    "Tags": "Rapporter/Evalueringer",
    "Shipping class": "",
    "Images": "",
    "Download limit": "",
    "Download expiry days": "",
    "Parent": "",
    "Grouped products": "",
    "Upsells": "",
    "Cross-sells": "",
    "External URL": "",
    "Button text": "",
    "Position": 0,
    "Meta: _wp_old_date": "2022-04-12",
    "Meta: _botiga_page_builder_mode": 0,
    "Meta: _botiga_sidebar_layout": "",
    "Meta: _botiga_disable_header_transparent": 0
  },
  {
    "ID": 36,
    "Type": "simple",
    "SKU": "",
    "Name": "SHOT Studentundersøkelse",
    "Published": 1,
    "Is featured?": 0,
    "Visibility in catalog": "visible",
    "Short description": "01.03.23",
    "Description": "Studentundersøkelse",
    "Date sale price starts": "",
    "Date sale price ends": "",
    "Tax status": "taxable",
    "Tax class": "",
    "In stock?": 1,
    "Stock": "",
    "Low stock amount": "",
    "Backorders allowed?": 0,
    "Sold individually?": 0,
    "Weight (kg)": "",
    "Length (cm)": "",
    "Width (cm)": "",
    "Height (cm)": "",
    "Allow customer reviews?": 1,
    "Purchase note": "",
    "Sale price": "",
    "Regular price": 1,
    "categories": ["Administrativt", "ANSATT", "Overordnet ansvar", "STUDENT", "Student - Campus", "Student-Online"],
    "Tags": "Rapporter/Evalueringer",
    "Shipping class": "",
    "Images": "",
    "Download limit": "",
    "Download expiry days": "",
    "Parent": "",
    "Grouped products": "",
    "Upsells": "",
    "Cross-sells": "",
    "External URL": "",
    "Button text": "",
    "Position": 0,
    "Meta: _wp_old_date": "2022-04-12",
    "Meta: _botiga_page_builder_mode": 0,
    "Meta: _botiga_sidebar_layout": "",
    "Meta: _botiga_disable_header_transparent": 0
  },
  {
    "ID": 38,
    "Type": "simple",
    "SKU": "",
    "Name": "Springbrettet Karrieredag",
    "Published": 1,
    "Is featured?": 0,
    "Visibility in catalog": "visible",
    "Short description": "21.09.22",
    "Description": "",
    "Date sale price starts": "",
    "Date sale price ends": "",
    "Tax status": "taxable",
    "Tax class": "",
    "In stock?": 1,
    "Stock": "",
    "Low stock amount": "",
    "Backorders allowed?": 0,
    "Sold individually?": 0,
    "Weight (kg)": "",
    "Length (cm)": "",
    "Width (cm)": "",
    "Height (cm)": "",
    "Allow customer reviews?": 1,
    "Purchase note": "",
    "Sale price": "",
    "Regular price": 2,
    "categories": ["STUDENT", "Student - Campus", "Student-Online"],
    "Tags": "Kontakt med næringslivet",
    "Shipping class": "",
    "Images": "",
    "Download limit": "",
    "Download expiry days": "",
    "Parent": "",
    "Grouped products": "",
    "Upsells": "",
    "Cross-sells": "",
    "External URL": "",
    "Button text": "",
    "Position": 0,
    "Meta: _wp_old_date": "2020-10-01",
    "Meta: _botiga_page_builder_mode": "",
    "Meta: _botiga_sidebar_layout": "",
    "Meta: _botiga_disable_header_transparent": ""
  },
  {
    "ID": 39,
    "Type": "simple",
    "SKU": "",
    "Name": "Caseløsning",
    "Published": 1,
    "Is featured?": 0,
    "Visibility in catalog": "visible",
    "Short description": "TBA",
    "Description": "v/Capgemini",
    "Date sale price starts": "",
    "Date sale price ends": "",
    "Tax status": "taxable",
    "Tax class": "",
    "In stock?": 1,
    "Stock": "",
    "Low stock amount": "",
    "Backorders allowed?": 0,
    "Sold individually?": 0,
    "Weight (kg)": "",
    "Length (cm)": "",
    "Width (cm)": "",
    "Height (cm)": "",
    "Allow customer reviews?": 1,
    "Purchase note": "",
    "Sale price": "",
    "Regular price": 2,
    "categories": ["STUDENT", "Student - Campus"],
    "Tags": "Arrangement, Kontakt med næringslivet",
    "Shipping class": "",
    "Images": "",
    "Download limit": "",
    "Download expiry days": "",
    "Parent": "",
    "Grouped products": "",
    "Upsells": "",
    "Cross-sells": "",
    "External URL": "",
    "Button text": "",
    "Position": 0,
    "Meta: _wp_old_date": "2022-04-12",
    "Meta: _botiga_page_builder_mode": "",
    "Meta: _botiga_sidebar_layout": "",
    "Meta: _botiga_disable_header_transparent": ""
  },
  {
    "ID": 40,
    "Type": "simple",
    "SKU": "",
    "Name": "Industry Talks - Høst",
    "Published": 1,
    "Is featured?": 0,
    "Visibility in catalog": "visible",
    "Short description": "Se program",
    "Description": "",
    "Date sale price starts": "",
    "Date sale price ends": "",
    "Tax status": "taxable",
    "Tax class": "",
    "In stock?": 1,
    "Stock": "",
    "Low stock amount": "",
    "Backorders allowed?": 0,
    "Sold individually?": 0,
    "Weight (kg)": "",
    "Length (cm)": "",
    "Width (cm)": "",
    "Height (cm)": "",
    "Allow customer reviews?": 1,
    "Purchase note": "",
    "Sale price": "",
    "Regular price": 2,
    "categories": ["STUDENT", "Student - Campus", "Student-Online"],
    "Tags": "Kontakt med næringslivet",
    "Shipping class": "",
    "Images": "",
    "Download limit": "",
    "Download expiry days": "",
    "Parent": "",
    "Grouped products": "",
    "Upsells": "",
    "Cross-sells": "",
    "External URL": "",
    "Button text": "",
    "Position": 0,
    "Meta: _wp_old_date": "2022-04-12",
    "Meta: _botiga_page_builder_mode": "",
    "Meta: _botiga_sidebar_layout": "",
    "Meta: _botiga_disable_header_transparent": ""
  },
  {
    "ID": 41,
    "Type": "simple",
    "SKU": "",
    "Name": "Industry Talks - Vår",
    "Published": 1,
    "Is featured?": 0,
    "Visibility in catalog": "visible",
    "Short description": "Se program",
    "Description": "",
    "Date sale price starts": "",
    "Date sale price ends": "",
    "Tax status": "taxable",
    "Tax class": "",
    "In stock?": 1,
    "Stock": "",
    "Low stock amount": "",
    "Backorders allowed?": 0,
    "Sold individually?": 0,
    "Weight (kg)": "",
    "Length (cm)": "",
    "Width (cm)": "",
    "Height (cm)": "",
    "Allow customer reviews?": 1,
    "Purchase note": "",
    "Sale price": "",
    "Regular price": 2,
    "categories": ["STUDENT", "Student - Campus", "Student-Online"],
    "Tags": "Kontakt med næringslivet",
    "Shipping class": "",
    "Images": "",
    "Download limit": "",
    "Download expiry days": "",
    "Parent": "",
    "Grouped products": "",
    "Upsells": "",
    "Cross-sells": "",
    "External URL": "",
    "Button text": "",
    "Position": 0,
    "Meta: _wp_old_date": "2022-04-12",
    "Meta: _botiga_page_builder_mode": "",
    "Meta: _botiga_sidebar_layout": "",
    "Meta: _botiga_disable_header_transparent": ""
  },
  {
    "ID": 42,
    "Type": "simple",
    "SKU": "",
    "Name": "NOROFF Bransjedag",
    "Published": 1,
    "Is featured?": 0,
    "Visibility in catalog": "visible",
    "Short description": "20.03.23",
    "Description": "Møte med arbeidsgivere og bransjen",
    "Date sale price starts": "",
    "Date sale price ends": "",
    "Tax status": "taxable",
    "Tax class": "",
    "In stock?": 1,
    "Stock": "",
    "Low stock amount": "",
    "Backorders allowed?": 0,
    "Sold individually?": 0,
    "Weight (kg)": "",
    "Length (cm)": "",
    "Width (cm)": "",
    "Height (cm)": "",
    "Allow customer reviews?": 1,
    "Purchase note": "",
    "Sale price": "",
    "Regular price": 2,
    "categories": ["Administrativt", "ANSATT", "STUDENT", "Student - Campus", "Student-Online"],
    "Tags": "Arrangement, Kontakt med næringslivet",
    "Shipping class": "",
    "Images": "",
    "Download limit": "",
    "Download expiry days": "",
    "Parent": "",
    "Grouped products": "",
    "Upsells": "",
    "Cross-sells": "",
    "External URL": "",
    "Button text": "",
    "Position": 0,
    "Meta: _wp_old_date": "2022-04-12",
    "Meta: _botiga_page_builder_mode": 0,
    "Meta: _botiga_sidebar_layout": "",
    "Meta: _botiga_disable_header_transparent": 0
  },
  {
    "ID": 43,
    "Type": "simple",
    "SKU": "",
    "Name": "Diamond Awards",
    "Published": 1,
    "Is featured?": 0,
    "Visibility in catalog": "visible",
    "Short description": "Se campus",
    "Description": "Skoleavslutning",
    "Date sale price starts": "",
    "Date sale price ends": "",
    "Tax status": "taxable",
    "Tax class": "",
    "In stock?": 1,
    "Stock": "",
    "Low stock amount": "",
    "Backorders allowed?": 0,
    "Sold individually?": 0,
    "Weight (kg)": "",
    "Length (cm)": "",
    "Width (cm)": "",
    "Height (cm)": "",
    "Allow customer reviews?": 1,
    "Purchase note": "",
    "Sale price": "",
    "Regular price": 3,
    "categories": ["Administrativt", "ANSATT", "STUDENT", "Student - Campus"],
    "Tags": "Arrangement",
    "Shipping class": "",
    "Images": "",
    "Download limit": "",
    "Download expiry days": "",
    "Parent": "",
    "Grouped products": "",
    "Upsells": "",
    "Cross-sells": "",
    "External URL": "",
    "Button text": "",
    "Position": 0,
    "Meta: _wp_old_date": "2022-04-12",
    "Meta: _botiga_page_builder_mode": 0,
    "Meta: _botiga_sidebar_layout": "",
    "Meta: _botiga_disable_header_transparent": 0
  },
  {
    "ID": 44,
    "Type": "simple",
    "SKU": "",
    "Name": "Sosialt Arrangement - Vår",
    "Published": 1,
    "Is featured?": 0,
    "Visibility in catalog": "visible",
    "Short description": "TBA",
    "Description": "Kommer",
    "Date sale price starts": "",
    "Date sale price ends": "",
    "Tax status": "taxable",
    "Tax class": "",
    "In stock?": 1,
    "Stock": "",
    "Low stock amount": "",
    "Backorders allowed?": 0,
    "Sold individually?": 0,
    "Weight (kg)": "",
    "Length (cm)": "",
    "Width (cm)": "",
    "Height (cm)": "",
    "Allow customer reviews?": 1,
    "Purchase note": "",
    "Sale price": "",
    "Regular price": 3,
    "categories": ["STUDENT", "Student - Campus"],
    "Tags": "Arrangement",
    "Shipping class": "",
    "Images": "",
    "Download limit": "",
    "Download expiry days": "",
    "Parent": "",
    "Grouped products": "",
    "Upsells": "",
    "Cross-sells": "",
    "External URL": "",
    "Button text": "",
    "Position": 0,
    "Meta: _wp_old_date": "2022-04-12",
    "Meta: _botiga_page_builder_mode": "",
    "Meta: _botiga_sidebar_layout": "",
    "Meta: _botiga_disable_header_transparent": ""
  },
  {
    "ID": 45,
    "Type": "simple",
    "SKU": "",
    "Name": "Sosialt Arrangement - Høst",
    "Published": 1,
    "Is featured?": 0,
    "Visibility in catalog": "visible",
    "Short description": "Kommer",
    "Description": "Høst",
    "Date sale price starts": "",
    "Date sale price ends": "",
    "Tax status": "taxable",
    "Tax class": "",
    "In stock?": 1,
    "Stock": "",
    "Low stock amount": "",
    "Backorders allowed?": 0,
    "Sold individually?": 0,
    "Weight (kg)": "",
    "Length (cm)": "",
    "Width (cm)": "",
    "Height (cm)": "",
    "Allow customer reviews?": 1,
    "Purchase note": "",
    "Sale price": "",
    "Regular price": 3,
    "categories": ["STUDENT", "Student - Campus"],
    "Tags": "Arrangement",
    "Shipping class": "",
    "Images": "",
    "Download limit": "",
    "Download expiry days": "",
    "Parent": "",
    "Grouped products": "",
    "Upsells": "",
    "Cross-sells": "",
    "External URL": "",
    "Button text": "",
    "Position": 0,
    "Meta: _wp_old_date": "2022-04-12",
    "Meta: _botiga_page_builder_mode": "",
    "Meta: _botiga_sidebar_layout": "",
    "Meta: _botiga_disable_header_transparent": ""
  },
  {
    "ID": 46,
    "Type": "simple",
    "SKU": "",
    "Name": "Valg av klasserepresentant",
    "Published": 1,
    "Is featured?": 0,
    "Visibility in catalog": "visible",
    "Short description": "Se info",
    "Description": "Internt for klasse",
    "Date sale price starts": "",
    "Date sale price ends": "",
    "Tax status": "taxable",
    "Tax class": "",
    "In stock?": 1,
    "Stock": "",
    "Low stock amount": "",
    "Backorders allowed?": 0,
    "Sold individually?": 0,
    "Weight (kg)": "",
    "Length (cm)": "",
    "Width (cm)": "",
    "Height (cm)": "",
    "Allow customer reviews?": 1,
    "Purchase note": "",
    "Sale price": "",
    "Regular price": 4,
    "categories": ["ANSATT", "Faglig ansvarlig", "STUDENT", "Student - Campus"],
    "Tags": "Valg/Deltakelse",
    "Shipping class": "",
    "Images": "",
    "Download limit": "",
    "Download expiry days": "",
    "Parent": "",
    "Grouped products": "",
    "Upsells": "",
    "Cross-sells": "",
    "External URL": "",
    "Button text": "",
    "Position": 0,
    "Meta: _wp_old_date": "2022-04-12",
    "Meta: _botiga_page_builder_mode": 0,
    "Meta: _botiga_sidebar_layout": "",
    "Meta: _botiga_disable_header_transparent": 0
  },
  {
    "ID": 47,
    "Type": "simple",
    "SKU": "",
    "Name": "Valg av studentråd",
    "Published": 1,
    "Is featured?": 0,
    "Visibility in catalog": "visible",
    "Short description": "September",
    "Description": "Nasjonalt og lokalt",
    "Date sale price starts": "",
    "Date sale price ends": "",
    "Tax status": "taxable",
    "Tax class": "",
    "In stock?": 1,
    "Stock": "",
    "Low stock amount": "",
    "Backorders allowed?": 0,
    "Sold individually?": 0,
    "Weight (kg)": "",
    "Length (cm)": "",
    "Width (cm)": "",
    "Height (cm)": "",
    "Allow customer reviews?": 1,
    "Purchase note": "",
    "Sale price": "",
    "Regular price": 4,
    "categories": ["Administrativt", "ANSATT", "STUDENT", "Student - Campus", "Student-Online"],
    "Tags": "Valg/Deltakelse",
    "Shipping class": "",
    "Images": "",
    "Download limit": "",
    "Download expiry days": "",
    "Parent": "",
    "Grouped products": "",
    "Upsells": "",
    "Cross-sells": "",
    "External URL": "",
    "Button text": "",
    "Position": 0,
    "Meta: _wp_old_date": "2022-04-12",
    "Meta: _botiga_page_builder_mode": 0,
    "Meta: _botiga_sidebar_layout": "",
    "Meta: _botiga_disable_header_transparent": 0
  },
  {
    "ID": 48,
    "Type": "simple",
    "SKU": "",
    "Name": "Valg av studentrepresentant",
    "Published": 1,
    "Is featured?": 0,
    "Visibility in catalog": "visible",
    "Short description": "September",
    "Description": "For styret",
    "Date sale price starts": "",
    "Date sale price ends": "",
    "Tax status": "taxable",
    "Tax class": "",
    "In stock?": 1,
    "Stock": "",
    "Low stock amount": "",
    "Backorders allowed?": 0,
    "Sold individually?": 0,
    "Weight (kg)": "",
    "Length (cm)": "",
    "Width (cm)": "",
    "Height (cm)": "",
    "Allow customer reviews?": 1,
    "Purchase note": "",
    "Sale price": "",
    "Regular price": 4,
    "categories": ["Administrativt", "ANSATT", "Overordnet ansvar", "STUDENT", "Student - Campus", "Student-Online"],
    "Tags": "Valg/Deltakelse",
    "Shipping class": "",
    "Images": "",
    "Download limit": "",
    "Download expiry days": "",
    "Parent": "",
    "Grouped products": "",
    "Upsells": "",
    "Cross-sells": "",
    "External URL": "",
    "Button text": "",
    "Position": 0,
    "Meta: _wp_old_date": "2022-04-12",
    "Meta: _botiga_page_builder_mode": 0,
    "Meta: _botiga_sidebar_layout": "",
    "Meta: _botiga_disable_header_transparent": 0
  },
  {
    "ID": 49,
    "Type": "simple",
    "SKU": "",
    "Name": "Valg: Klagenemda",
    "Published": 1,
    "Is featured?": 0,
    "Visibility in catalog": "visible",
    "Short description": "September",
    "Description": "Studentrepresentant",
    "Date sale price starts": "",
    "Date sale price ends": "",
    "Tax status": "taxable",
    "Tax class": "",
    "In stock?": 1,
    "Stock": "",
    "Low stock amount": "",
    "Backorders allowed?": 0,
    "Sold individually?": 0,
    "Weight (kg)": "",
    "Length (cm)": "",
    "Width (cm)": "",
    "Height (cm)": "",
    "Allow customer reviews?": 1,
    "Purchase note": "",
    "Sale price": "",
    "Regular price": 4,
    "categories": ["Administrativt", "ANSATT", "STUDENT", "Student - Campus", "Student-Online"],
    "Tags": "Valg/Deltakelse",
    "Shipping class": "",
    "Images": "",
    "Download limit": "",
    "Download expiry days": "",
    "Parent": "",
    "Grouped products": "",
    "Upsells": "",
    "Cross-sells": "",
    "External URL": "",
    "Button text": "",
    "Position": 0,
    "Meta: _wp_old_date": "2022-04-12",
    "Meta: _botiga_page_builder_mode": 0,
    "Meta: _botiga_sidebar_layout": "",
    "Meta: _botiga_disable_header_transparent": 0
  },
  {
    "ID": 50,
    "Type": "simple",
    "SKU": "",
    "Name": "Skolestart",
    "Published": 1,
    "Is featured?": 0,
    "Visibility in catalog": "visible",
    "Short description": "16.08.22",
    "Description": "",
    "Date sale price starts": "",
    "Date sale price ends": "",
    "Tax status": "taxable",
    "Tax class": "",
    "In stock?": 1,
    "Stock": "",
    "Low stock amount": "",
    "Backorders allowed?": 0,
    "Sold individually?": 0,
    "Weight (kg)": "",
    "Length (cm)": "",
    "Width (cm)": "",
    "Height (cm)": "",
    "Allow customer reviews?": 1,
    "Purchase note": "",
    "Sale price": "",
    "Regular price": 5,
    "categories": ["Administrativt", "ANSATT", "Faglig ansvarlig", "Overordnet ansvar", "STUDENT", "Student - Campus", "Student-Online"],
    "Tags": "Viktige datoer",
    "Shipping class": "",
    "Images": "",
    "Download limit": "",
    "Download expiry days": "",
    "Parent": "",
    "Grouped products": "",
    "Upsells": "",
    "Cross-sells": "",
    "External URL": "",
    "Button text": "",
    "Position": 0,
    "Meta: _wp_old_date": "2022-04-12",
    "Meta: _botiga_page_builder_mode": 0,
    "Meta: _botiga_sidebar_layout": "",
    "Meta: _botiga_disable_header_transparent": 0
  },
  {
    "ID": 51,
    "Type": "simple",
    "SKU": "",
    "Name": "Registrering: Online",
    "Published": 1,
    "Is featured?": 0,
    "Visibility in catalog": "visible",
    "Short description": "Se kurs",
    "Description": "Studier uten ordinær oppstart",
    "Date sale price starts": "",
    "Date sale price ends": "",
    "Tax status": "taxable",
    "Tax class": "",
    "In stock?": 1,
    "Stock": "",
    "Low stock amount": "",
    "Backorders allowed?": 0,
    "Sold individually?": 0,
    "Weight (kg)": "",
    "Length (cm)": "",
    "Width (cm)": "",
    "Height (cm)": "",
    "Allow customer reviews?": 1,
    "Purchase note": "",
    "Sale price": "",
    "Regular price": 5,
    "categories": ["Administrativt", "ANSATT", "STUDENT", "Student-Online"],
    "Tags": "Viktige datoer",
    "Shipping class": "",
    "Images": "",
    "Download limit": "",
    "Download expiry days": "",
    "Parent": "",
    "Grouped products": "",
    "Upsells": "",
    "Cross-sells": "",
    "External URL": "",
    "Button text": "",
    "Position": 0,
    "Meta: _wp_old_date": "2022-04-12",
    "Meta: _botiga_page_builder_mode": 0,
    "Meta: _botiga_sidebar_layout": "",
    "Meta: _botiga_disable_header_transparent": 0
  },
  {
    "ID": 52,
    "Type": "simple",
    "SKU": "",
    "Name": "Registrering åpner",
    "Published": 1,
    "Is featured?": 0,
    "Visibility in catalog": "visible",
    "Short description": "01.02.23",
    "Description": "",
    "Date sale price starts": "",
    "Date sale price ends": "",
    "Tax status": "taxable",
    "Tax class": "",
    "In stock?": 1,
    "Stock": "",
    "Low stock amount": "",
    "Backorders allowed?": 0,
    "Sold individually?": 0,
    "Weight (kg)": "",
    "Length (cm)": "",
    "Width (cm)": "",
    "Height (cm)": "",
    "Allow customer reviews?": 1,
    "Purchase note": "",
    "Sale price": "",
    "Regular price": 5,
    "categories": ["Administrativt", "ANSATT", "Ny student", "STUDENT"],
    "Tags": "Viktige datoer",
    "Shipping class": "",
    "Images": "",
    "Download limit": "",
    "Download expiry days": "",
    "Parent": "",
    "Grouped products": "",
    "Upsells": "",
    "Cross-sells": "",
    "External URL": "",
    "Button text": "",
    "Position": 0,
    "Meta: _wp_old_date": "2022-04-12",
    "Meta: _botiga_page_builder_mode": 0,
    "Meta: _botiga_sidebar_layout": "",
    "Meta: _botiga_disable_header_transparent": 0
  },
  {
    "ID": 53,
    "Type": "simple",
    "SKU": "",
    "Name": "Offisielt: Siste skoledag",
    "Published": 1,
    "Is featured?": 0,
    "Visibility in catalog": "visible",
    "Short description": "Se campus",
    "Description": "",
    "Date sale price starts": "",
    "Date sale price ends": "",
    "Tax status": "taxable",
    "Tax class": "",
    "In stock?": 1,
    "Stock": "",
    "Low stock amount": "",
    "Backorders allowed?": 0,
    "Sold individually?": 0,
    "Weight (kg)": "",
    "Length (cm)": "",
    "Width (cm)": "",
    "Height (cm)": "",
    "Allow customer reviews?": 1,
    "Purchase note": "",
    "Sale price": "",
    "Regular price": 5,
    "categories": ["Administrativt", "ANSATT", "Faglig ansvarlig", "Overordnet ansvar", "STUDENT", "Student - Campus", "Student-Online"],
    "Tags": "Viktige datoer",
    "Shipping class": "",
    "Images": "",
    "Download limit": "",
    "Download expiry days": "",
    "Parent": "",
    "Grouped products": "",
    "Upsells": "",
    "Cross-sells": "",
    "External URL": "",
    "Button text": "",
    "Position": 0,
    "Meta: _wp_old_date": "2022-04-12",
    "Meta: _botiga_page_builder_mode": 0,
    "Meta: _botiga_sidebar_layout": "",
    "Meta: _botiga_disable_header_transparent": 0
  },
  {
    "ID": 63,
    "Type": "simple",
    "SKU": "",
    "Name": "Data/Statistikk",
    "Published": 1,
    "Is featured?": 0,
    "Visibility in catalog": "visible",
    "Short description": "31.10.2022",
    "Description": "Til kvalitetsrapport",
    "Date sale price starts": "",
    "Date sale price ends": "",
    "Tax status": "taxable",
    "Tax class": "",
    "In stock?": 1,
    "Stock": "",
    "Low stock amount": "",
    "Backorders allowed?": 0,
    "Sold individually?": 0,
    "Weight (kg)": "",
    "Length (cm)": "",
    "Width (cm)": "",
    "Height (cm)": "",
    "Allow customer reviews?": 1,
    "Purchase note": "",
    "Sale price": "",
    "Regular price": "",
    "categories": "Administrativt, ANSATT, Overordnet ansvar",
    "Tags": "Rapporter/Evalueringer",
    "Shipping class": "",
    "Images": "",
    "Download limit": "",
    "Download expiry days": "",
    "Parent": "",
    "Grouped products": "",
    "Upsells": "",
    "Cross-sells": "",
    "External URL": "",
    "Button text": "",
    "Position": 0,
    "Meta: _wp_old_date": "2022-04-18",
    "Meta: _botiga_page_builder_mode": 0,
    "Meta: _botiga_sidebar_layout": "",
    "Meta: _botiga_disable_header_transparent": 0
  },
  {
    "ID": 64,
    "Type": "simple",
    "SKU": "",
    "Name": "Halvtårsrapport",
    "Published": 1,
    "Is featured?": 0,
    "Visibility in catalog": "visible",
    "Short description": "01.01.23",
    "Description": "",
    "Date sale price starts": "",
    "Date sale price ends": "",
    "Tax status": "taxable",
    "Tax class": "",
    "In stock?": 1,
    "Stock": "",
    "Low stock amount": "",
    "Backorders allowed?": 0,
    "Sold individually?": 0,
    "Weight (kg)": "",
    "Length (cm)": "",
    "Width (cm)": "",
    "Height (cm)": "",
    "Allow customer reviews?": 1,
    "Purchase note": "",
    "Sale price": "",
    "Regular price": "",
    "categories": "ANSATT, Overordnet ansvar",
    "Tags": "Rapporter/Evalueringer",
    "Shipping class": "",
    "Images": "",
    "Download limit": "",
    "Download expiry days": "",
    "Parent": "",
    "Grouped products": "",
    "Upsells": "",
    "Cross-sells": "",
    "External URL": "",
    "Button text": "",
    "Position": 0,
    "Meta: _wp_old_date": "2022-04-18",
    "Meta: _botiga_page_builder_mode": 0,
    "Meta: _botiga_sidebar_layout": "",
    "Meta: _botiga_disable_header_transparent": 0
  },
  {
    "ID": 65,
    "Type": "simple",
    "SKU": "",
    "Name": "Årlig kvalitetsrapport",
    "Published": 1,
    "Is featured?": 0,
    "Visibility in catalog": "visible",
    "Short description": "31.03.23",
    "Description": "Forrige skoleår",
    "Date sale price starts": "",
    "Date sale price ends": "",
    "Tax status": "taxable",
    "Tax class": "",
    "In stock?": 1,
    "Stock": "",
    "Low stock amount": "",
    "Backorders allowed?": 0,
    "Sold individually?": 0,
    "Weight (kg)": "",
    "Length (cm)": "",
    "Width (cm)": "",
    "Height (cm)": "",
    "Allow customer reviews?": 1,
    "Purchase note": "",
    "Sale price": "",
    "Regular price": "",
    "categories": "Administrativt, ANSATT, Overordnet ansvar",
    "Tags": "Rapporter/Evalueringer",
    "Shipping class": "",
    "Images": "",
    "Download limit": "",
    "Download expiry days": "",
    "Parent": "",
    "Grouped products": "",
    "Upsells": "",
    "Cross-sells": "",
    "External URL": "",
    "Button text": "",
    "Position": 0,
    "Meta: _wp_old_date": "2022-04-18",
    "Meta: _botiga_page_builder_mode": 0,
    "Meta: _botiga_sidebar_layout": "",
    "Meta: _botiga_disable_header_transparent": 0
  },
  {
    "ID": 66,
    "Type": "simple",
    "SKU": "",
    "Name": "Rapport: Helhetsvurdering",
    "Published": 1,
    "Is featured?": 0,
    "Visibility in catalog": "visible",
    "Short description": "30.09.2022",
    "Description": "Uteksaminerte studenter",
    "Date sale price starts": "",
    "Date sale price ends": "",
    "Tax status": "taxable",
    "Tax class": "",
    "In stock?": 1,
    "Stock": "",
    "Low stock amount": "",
    "Backorders allowed?": 0,
    "Sold individually?": 0,
    "Weight (kg)": "",
    "Length (cm)": "",
    "Width (cm)": "",
    "Height (cm)": "",
    "Allow customer reviews?": 1,
    "Purchase note": "",
    "Sale price": "",
    "Regular price": "",
    "categories": "Administrativt, ANSATT, Faglig ansvarlig, Overordnet ansvar, Uncategorized",
    "Tags": "Rapporter/Evalueringer",
    "Shipping class": "",
    "Images": "",
    "Download limit": "",
    "Download expiry days": "",
    "Parent": "",
    "Grouped products": "",
    "Upsells": "",
    "Cross-sells": "",
    "External URL": "",
    "Button text": "",
    "Position": 0,
    "Meta: _wp_old_date": "2022-04-18",
    "Meta: _botiga_page_builder_mode": 0,
    "Meta: _botiga_sidebar_layout": "",
    "Meta: _botiga_disable_header_transparent": 0
  },
  {
    "ID": 67,
    "Type": "simple",
    "SKU": "",
    "Name": "Statusrapport: Ansatte",
    "Published": 1,
    "Is featured?": 0,
    "Visibility in catalog": "visible",
    "Short description": "01.12.22",
    "Description": "",
    "Date sale price starts": "",
    "Date sale price ends": "",
    "Tax status": "taxable",
    "Tax class": "",
    "In stock?": 1,
    "Stock": "",
    "Low stock amount": "",
    "Backorders allowed?": 0,
    "Sold individually?": 0,
    "Weight (kg)": "",
    "Length (cm)": "",
    "Width (cm)": "",
    "Height (cm)": "",
    "Allow customer reviews?": 1,
    "Purchase note": "",
    "Sale price": "",
    "Regular price": "",
    "categories": "Administrativt, ANSATT, Faglig ansvarlig, Overordnet ansvar",
    "Tags": "Rapporter/Evalueringer",
    "Shipping class": "",
    "Images": "",
    "Download limit": "",
    "Download expiry days": "",
    "Parent": "",
    "Grouped products": "",
    "Upsells": "",
    "Cross-sells": "",
    "External URL": "",
    "Button text": "",
    "Position": 0,
    "Meta: _wp_old_date": "2022-04-18",
    "Meta: _botiga_page_builder_mode": 0,
    "Meta: _botiga_sidebar_layout": "",
    "Meta: _botiga_disable_header_transparent": 0
  },
  {
    "ID": 68,
    "Type": "simple",
    "SKU": "",
    "Name": "Fagskolestudier",
    "Published": 1,
    "Is featured?": 0,
    "Visibility in catalog": "visible",
    "Short description": "TBA",
    "Description": "Nasjonalt informasjonsmøte",
    "Date sale price starts": "",
    "Date sale price ends": "",
    "Tax status": "taxable",
    "Tax class": "",
    "In stock?": 1,
    "Stock": "",
    "Low stock amount": "",
    "Backorders allowed?": 0,
    "Sold individually?": 0,
    "Weight (kg)": "",
    "Length (cm)": "",
    "Width (cm)": "",
    "Height (cm)": "",
    "Allow customer reviews?": 1,
    "Purchase note": "",
    "Sale price": "",
    "Regular price": "",
    "categories": "ANSATT, Faglig ansvarlig, Overordnet ansvar, Uncategorized",
    "Tags": "Arrangement",
    "Shipping class": "",
    "Images": "",
    "Download limit": "",
    "Download expiry days": "",
    "Parent": "",
    "Grouped products": "",
    "Upsells": "",
    "Cross-sells": "",
    "External URL": "",
    "Button text": "",
    "Position": 0,
    "Meta: _wp_old_date": "2022-04-18",
    "Meta: _botiga_page_builder_mode": 0,
    "Meta: _botiga_sidebar_layout": "",
    "Meta: _botiga_disable_header_transparent": 0
  },
  {
    "ID": 69,
    "Type": "simple",
    "SKU": "",
    "Name": "Beslutte studieprogram",
    "Published": 1,
    "Is featured?": 0,
    "Visibility in catalog": "visible",
    "Short description": "31.01.23",
    "Description": "Kommende skoleår",
    "Date sale price starts": "",
    "Date sale price ends": "",
    "Tax status": "taxable",
    "Tax class": "",
    "In stock?": 1,
    "Stock": "",
    "Low stock amount": "",
    "Backorders allowed?": 0,
    "Sold individually?": 0,
    "Weight (kg)": "",
    "Length (cm)": "",
    "Width (cm)": "",
    "Height (cm)": "",
    "Allow customer reviews?": 1,
    "Purchase note": "",
    "Sale price": "",
    "Regular price": "",
    "categories": "Administrativt, ANSATT, Faglig ansvarlig, Overordnet ansvar",
    "Tags": "Søknader/Beslutninger",
    "Shipping class": "",
    "Images": "",
    "Download limit": "",
    "Download expiry days": "",
    "Parent": "",
    "Grouped products": "",
    "Upsells": "",
    "Cross-sells": "",
    "External URL": "",
    "Button text": "",
    "Position": 0,
    "Meta: _wp_old_date": "2022-04-19",
    "Meta: _botiga_page_builder_mode": 0,
    "Meta: _botiga_sidebar_layout": "",
    "Meta: _botiga_disable_header_transparent": 0
  },
  {
    "ID": 70,
    "Type": "simple",
    "SKU": "",
    "Name": "Endring i studieprogram",
    "Published": 1,
    "Is featured?": 0,
    "Visibility in catalog": "visible",
    "Short description": "25.02.23",
    "Description": "NOKUT",
    "Date sale price starts": "",
    "Date sale price ends": "",
    "Tax status": "taxable",
    "Tax class": "",
    "In stock?": 1,
    "Stock": "",
    "Low stock amount": "",
    "Backorders allowed?": 0,
    "Sold individually?": 0,
    "Weight (kg)": "",
    "Length (cm)": "",
    "Width (cm)": "",
    "Height (cm)": "",
    "Allow customer reviews?": 1,
    "Purchase note": "",
    "Sale price": "",
    "Regular price": "",
    "categories": "Administrativt, ANSATT, Faglig ansvarlig, Overordnet ansvar",
    "Tags": "Søknader/Beslutninger",
    "Shipping class": "",
    "Images": "",
    "Download limit": "",
    "Download expiry days": "",
    "Parent": "",
    "Grouped products": "",
    "Upsells": "",
    "Cross-sells": "",
    "External URL": "",
    "Button text": "",
    "Position": 0,
    "Meta: _wp_old_date": "2022-04-19",
    "Meta: _botiga_page_builder_mode": 0,
    "Meta: _botiga_sidebar_layout": "",
    "Meta: _botiga_disable_header_transparent": 0
  },
  {
    "ID": 71,
    "Type": "simple",
    "SKU": "",
    "Name": "Budsjettvedtak",
    "Published": 1,
    "Is featured?": 0,
    "Visibility in catalog": "visible",
    "Short description": "Mai",
    "Description": "Kommende skoleår",
    "Date sale price starts": "",
    "Date sale price ends": "",
    "Tax status": "taxable",
    "Tax class": "",
    "In stock?": 1,
    "Stock": "",
    "Low stock amount": "",
    "Backorders allowed?": 0,
    "Sold individually?": 0,
    "Weight (kg)": "",
    "Length (cm)": "",
    "Width (cm)": "",
    "Height (cm)": "",
    "Allow customer reviews?": 1,
    "Purchase note": "",
    "Sale price": "",
    "Regular price": "",
    "categories": ["ANSATT", "Overordnet ansvar"],
    "Tags": "Søknader/Beslutninger",
    "Shipping class": "",
    "Images": "",
    "Download limit": "",
    "Download expiry days": "",
    "Parent": "",
    "Grouped products": "",
    "Upsells": "",
    "Cross-sells": "",
    "External URL": "",
    "Button text": "",
    "Position": 0,
    "Meta: _wp_old_date": "2022-04-19",
    "Meta: _botiga_page_builder_mode": 0,
    "Meta: _botiga_sidebar_layout": "",
    "Meta: _botiga_disable_header_transparent": 0
  },
  {
    "ID": 72,
    "Type": "simple",
    "SKU": "",
    "Name": "Beslutte studieportefølje",
    "Published": 1,
    "Is featured?": 0,
    "Visibility in catalog": "visible",
    "Short description": "TBA",
    "Description": "Kommende skoleår",
    "Date sale price starts": "",
    "Date sale price ends": "",
    "Tax status": "taxable",
    "Tax class": "",
    "In stock?": 1,
    "Stock": "",
    "Low stock amount": "",
    "Backorders allowed?": 0,
    "Sold individually?": 0,
    "Weight (kg)": "",
    "Length (cm)": "",
    "Width (cm)": "",
    "Height (cm)": "",
    "Allow customer reviews?": 1,
    "Purchase note": "",
    "Sale price": "",
    "Regular price": "",
    "categories": ["ANSATT", "Faglig ansvarlig", "Overordnet ansvar"],
    "Tags": "Søknader/Beslutninger",
    "Shipping class": "",
    "Images": "",
    "Download limit": "",
    "Download expiry days": "",
    "Parent": "",
    "Grouped products": "",
    "Upsells": "",
    "Cross-sells": "",
    "External URL": "",
    "Button text": "",
    "Position": 0,
    "Meta: _wp_old_date": "2022-04-19",
    "Meta: _botiga_page_builder_mode": 0,
    "Meta: _botiga_sidebar_layout": "",
    "Meta: _botiga_disable_header_transparent": 0
  },
  {
    "ID": 73,
    "Type": "simple",
    "SKU": "",
    "Name": "Sensurfrist",
    "Published": 1,
    "Is featured?": 0,
    "Visibility in catalog": "visible",
    "Short description": "TBA",
    "Description": "",
    "Date sale price starts": "",
    "Date sale price ends": "",
    "Tax status": "taxable",
    "Tax class": "",
    "In stock?": 1,
    "Stock": "",
    "Low stock amount": "",
    "Backorders allowed?": 0,
    "Sold individually?": 0,
    "Weight (kg)": "",
    "Length (cm)": "",
    "Width (cm)": "",
    "Height (cm)": "",
    "Allow customer reviews?": 1,
    "Purchase note": "",
    "Sale price": "",
    "Regular price": "",
    "categories": ["Administrativt", "ANSATT", "Faglig ansvarlig"],
    "Tags": "Viktige datoer",
    "Shipping class": "",
    "Images": "",
    "Download limit": "",
    "Download expiry days": "",
    "Parent": "",
    "Grouped products": "",
    "Upsells": "",
    "Cross-sells": "",
    "External URL": "",
    "Button text": "",
    "Position": 0,
    "Meta: _wp_old_date": "2022-04-19",
    "Meta: _botiga_page_builder_mode": 0,
    "Meta: _botiga_sidebar_layout": "",
    "Meta: _botiga_disable_header_transparent": 0
  }
]

